makasuipatch/__init__.py
makasuipatch/apps.py
makasuipatch/decode_simplepro_file.py
makasuipatch-0.0.4.dist-info/LICENSE
makasuipatch-0.0.4.dist-info/METADATA
makasuipatch-0.0.4.dist-info/WHEEL
makasuipatch-0.0.4.dist-info/top_level.txt
makasuipatch-0.0.4.dist-info/RECORD
