Metadata-Version: 2.1
Name: makasuipatch
Version: 0.0.4
Summary: A patch to simple pro to make you activate it. Just used for learning.
Author-email: makabaka <izhangxm@gmail.com>
Project-URL: Homepage, https://github.com/izhangxm/makasuipatch
Project-URL: Bug Tracker, https://github.com/izhangxm/makasuipatch/issues
Classifier: Programming Language :: Python :: 3
Classifier: License :: OSI Approved :: MIT License
Classifier: Operating System :: OS Independent
Requires-Python: >=3.0
License-File: LICENSE
Requires-Dist: simplepro
